{ "TEMP_UNIT_F": 0,
"TEMP_UNIT_C": 1,
"WEIGHT_UNIT_KG": 0,
"WEIGHT_UNIT_POUND": 1,
"MOOD_COOL": 1,
"MOOD_HEAT": 2,
"LANG_TYPE_KOR": 0,
"LANG_TYPE_ENG": 1,
"tempLangStr": "ENG",
"tempUnitString": "C",
"pressureUnitString": "kPa",
"weightUnitString": "TEXT_UNIT_WEIGHT",
"installerName": "울산동구 구강검진센터 3층(24마력-2)",
"installerInfo": "TEXT_INSTALLER_INFO",
"inspectorName": "(주)아이테크",
"inspectorInfo": "TEXT_INSPECTOR_INFO",
"managerName": "박정도",
"managerInfo": "TEXT_MANAGER_INFO",
"siteName": "울산동구 구강검진센터 3층(24마력-2)",
"siteInfo": "TEXT_SITE_INFO",
"modelType": "Multi V 5",
"userModelName": "RPUW12GX9E",
"writeDate": "2021년 07월 08일 13:07:52",
"odu1Version": "1.48.0 / 1.48.0",
"odu2Version": "TEXT_ODU2_VERSION_INFO",
"odu3Version": "TEXT_ODU3_VERSION_INFO",
"odu4Version": "TEXT_ODU4_VERSION_INFO",
"oduNumber": "2",
"iduNumber": "10",
"hruNumber": "0",
"iduTemp": "27.60",
"oduTemp": "29.70",
"runCycleInfo": "1",
"totalRefgVolume": "29.80",
"refgResultVolume": "-1.60",
"systemErrorInfo": "0",
"refgErrorInfo": "0",
"oduErrorInfo": "0",
"iduErrorInfo": "0",
"tempErrorInfo": "0",
"capacityErrorInfo": "0",
"masterEEVErrorInfo": "0",
"slave1EEVErrorInfo": "0",
"slave2EEVErrorInfo": "0",
"slave3EEVErrorInfo": "0",
"E05Reason": "0",
"iduTempMin": "26.50",
"iduTempMax": "28.30",
"basicRef": "17.00",
"iduEevErrorArray": [ "0", "0", "0", "0", "0", "0", "0", "0", "0", "0", "0", "0", "0", "0", "0", "0", "0", "0", "0", "0", "0", "0", "0", "0", "0", "0", "0", "0", "0", "0", "0", "0", "0", "0", "0", "0", "0", "0", "0", "0", "0", "0", "0", "0", "0", "0", "0", "0", "0", "0", "0", "0", "0", "0", "0", "0", "0", "0", "0", "0", "0", "0", "0", "0"],
"IduModelNameArray": ["", "", "", "", "", "", "", "", "", "", "ID_ITR_IDU_MODEL_NAME_11", "ID_ITR_IDU_MODEL_NAME_12", "ID_ITR_IDU_MODEL_NAME_13", "ID_ITR_IDU_MODEL_NAME_14", "ID_ITR_IDU_MODEL_NAME_15", "ID_ITR_IDU_MODEL_NAME_16", "ID_ITR_IDU_MODEL_NAME_17", "ID_ITR_IDU_MODEL_NAME_18", "ID_ITR_IDU_MODEL_NAME_19", "ID_ITR_IDU_MODEL_NAME_20", "ID_ITR_IDU_MODEL_NAME_21", "ID_ITR_IDU_MODEL_NAME_22", "ID_ITR_IDU_MODEL_NAME_23", "ID_ITR_IDU_MODEL_NAME_24", "ID_ITR_IDU_MODEL_NAME_25", "ID_ITR_IDU_MODEL_NAME_26", "ID_ITR_IDU_MODEL_NAME_27", "ID_ITR_IDU_MODEL_NAME_28", "ID_ITR_IDU_MODEL_NAME_29", "ID_ITR_IDU_MODEL_NAME_30", "ID_ITR_IDU_MODEL_NAME_31", "ID_ITR_IDU_MODEL_NAME_32", "ID_ITR_IDU_MODEL_NAME_33", "ID_ITR_IDU_MODEL_NAME_34", "ID_ITR_IDU_MODEL_NAME_35", "ID_ITR_IDU_MODEL_NAME_36", "ID_ITR_IDU_MODEL_NAME_37", "ID_ITR_IDU_MODEL_NAME_38", "ID_ITR_IDU_MODEL_NAME_39", "ID_ITR_IDU_MODEL_NAME_40", "ID_ITR_IDU_MODEL_NAME_41", "ID_ITR_IDU_MODEL_NAME_42", "ID_ITR_IDU_MODEL_NAME_43", "ID_ITR_IDU_MODEL_NAME_44", "ID_ITR_IDU_MODEL_NAME_45", "ID_ITR_IDU_MODEL_NAME_46", "ID_ITR_IDU_MODEL_NAME_47", "ID_ITR_IDU_MODEL_NAME_48", "ID_ITR_IDU_MODEL_NAME_49", "ID_ITR_IDU_MODEL_NAME_50", "ID_ITR_IDU_MODEL_NAME_51", "ID_ITR_IDU_MODEL_NAME_52", "ID_ITR_IDU_MODEL_NAME_53", "ID_ITR_IDU_MODEL_NAME_54", "ID_ITR_IDU_MODEL_NAME_55", "ID_ITR_IDU_MODEL_NAME_56", "ID_ITR_IDU_MODEL_NAME_57", "ID_ITR_IDU_MODEL_NAME_58", "ID_ITR_IDU_MODEL_NAME_59", "ID_ITR_IDU_MODEL_NAME_60", "ID_ITR_IDU_MODEL_NAME_61", "ID_ITR_IDU_MODEL_NAME_62", "ID_ITR_IDU_MODEL_NAME_63", "ID_ITR_IDU_MODEL_NAME_64"],
"IduSerialNumArray": ["", "", "", "", "", "", "", "", "", "", "ID_ITR_IDU_SERIAL_NUM_11", "ID_ITR_IDU_SERIAL_NUM_12", "ID_ITR_IDU_SERIAL_NUM_13", "ID_ITR_IDU_SERIAL_NUM_14", "ID_ITR_IDU_SERIAL_NUM_15", "ID_ITR_IDU_SERIAL_NUM_16", "ID_ITR_IDU_SERIAL_NUM_17", "ID_ITR_IDU_SERIAL_NUM_18", "ID_ITR_IDU_SERIAL_NUM_19", "ID_ITR_IDU_SERIAL_NUM_20", "ID_ITR_IDU_SERIAL_NUM_21", "ID_ITR_IDU_SERIAL_NUM_22", "ID_ITR_IDU_SERIAL_NUM_23", "ID_ITR_IDU_SERIAL_NUM_24", "ID_ITR_IDU_SERIAL_NUM_25", "ID_ITR_IDU_SERIAL_NUM_26", "ID_ITR_IDU_SERIAL_NUM_27", "ID_ITR_IDU_SERIAL_NUM_28", "ID_ITR_IDU_SERIAL_NUM_29", "ID_ITR_IDU_SERIAL_NUM_30", "ID_ITR_IDU_SERIAL_NUM_31", "ID_ITR_IDU_SERIAL_NUM_32", "ID_ITR_IDU_SERIAL_NUM_33", "ID_ITR_IDU_SERIAL_NUM_34", "ID_ITR_IDU_SERIAL_NUM_35", "ID_ITR_IDU_SERIAL_NUM_36", "ID_ITR_IDU_SERIAL_NUM_37", "ID_ITR_IDU_SERIAL_NUM_38", "ID_ITR_IDU_SERIAL_NUM_39", "ID_ITR_IDU_SERIAL_NUM_40", "ID_ITR_IDU_SERIAL_NUM_41", "ID_ITR_IDU_SERIAL_NUM_42", "ID_ITR_IDU_SERIAL_NUM_43", "ID_ITR_IDU_SERIAL_NUM_44", "ID_ITR_IDU_SERIAL_NUM_45", "ID_ITR_IDU_SERIAL_NUM_46", "ID_ITR_IDU_SERIAL_NUM_47", "ID_ITR_IDU_SERIAL_NUM_48", "ID_ITR_IDU_SERIAL_NUM_49", "ID_ITR_IDU_SERIAL_NUM_50", "ID_ITR_IDU_SERIAL_NUM_51", "ID_ITR_IDU_SERIAL_NUM_52", "ID_ITR_IDU_SERIAL_NUM_53", "ID_ITR_IDU_SERIAL_NUM_54", "ID_ITR_IDU_SERIAL_NUM_55", "ID_ITR_IDU_SERIAL_NUM_56", "ID_ITR_IDU_SERIAL_NUM_57", "ID_ITR_IDU_SERIAL_NUM_58", "ID_ITR_IDU_SERIAL_NUM_59", "ID_ITR_IDU_SERIAL_NUM_60", "ID_ITR_IDU_SERIAL_NUM_61", "ID_ITR_IDU_SERIAL_NUM_62", "ID_ITR_IDU_SERIAL_NUM_63", "ID_ITR_IDU_SERIAL_NUM_64"],
"HruModelNameArray": ["ID_ITR_HRU_MODEL_NAME_01", "ID_ITR_HRU_MODEL_NAME_02", "ID_ITR_HRU_MODEL_NAME_03", "ID_ITR_HRU_MODEL_NAME_04", "ID_ITR_HRU_MODEL_NAME_05", "ID_ITR_HRU_MODEL_NAME_06", "ID_ITR_HRU_MODEL_NAME_07", "ID_ITR_HRU_MODEL_NAME_08", "ID_ITR_HRU_MODEL_NAME_09", "ID_ITR_HRU_MODEL_NAME_10", "ID_ITR_HRU_MODEL_NAME_11", "ID_ITR_HRU_MODEL_NAME_12", "ID_ITR_HRU_MODEL_NAME_13", "ID_ITR_HRU_MODEL_NAME_14", "ID_ITR_HRU_MODEL_NAME_15", "ID_ITR_HRU_MODEL_NAME_16"],
"HruSerialNumArray": ["ID_ITR_HRU_SERIAL_NUM_01", "ID_ITR_HRU_SERIAL_NUM_02", "ID_ITR_HRU_SERIAL_NUM_03", "ID_ITR_HRU_SERIAL_NUM_04", "ID_ITR_HRU_SERIAL_NUM_05", "ID_ITR_HRU_SERIAL_NUM_06", "ID_ITR_HRU_SERIAL_NUM_07", "ID_ITR_HRU_SERIAL_NUM_08", "ID_ITR_HRU_SERIAL_NUM_09", "ID_ITR_HRU_SERIAL_NUM_10", "ID_ITR_HRU_SERIAL_NUM_11", "ID_ITR_HRU_SERIAL_NUM_12", "ID_ITR_HRU_SERIAL_NUM_13", "ID_ITR_HRU_SERIAL_NUM_14", "ID_ITR_HRU_SERIAL_NUM_15", "ID_ITR_HRU_SERIAL_NUM_16"],
"masterHighPressureMin": "2173",
"masterHighPressureMax": "2239",
"masterHighPressureAvg": "2173",
"slave1HighPressureMin": "2141",
"slave1HighPressureMax": "2239",
"slave1HighPressureAvg": "2141",
"slave2HighPressureMin": "0",
"slave2HighPressureMax": "0",
"slave2HighPressureAvg": "0",
"slave3HighPressureMin": "0",
"slave3HighPressureMax": "0",
"slave3HighPressureAvg": "0",
"masterEEVMin": "32",
"masterEEVMax": "32",
"masterEEVAvg": "32",
"slave1EEVMin": "32",
"slave1EEVMax": "32",
"slave1EEVAvg": "32",
"slave2EEVMin": "0",
"slave2EEVMax": "0",
"slave2EEVAvg": "0",
"slave3EEVMin": "0",
"slave3EEVMax": "0",
"slave3EEVAvg": "0",
"masterDischargeSHAvg": "37.50",
"slave1DischargeSHAvg": "37.50",
"slave2DischargeSHAvg": "0.00",
"slave3DischargeSHAvg": "0.00",
"masterSutionSHAvg": "19.00",
"slave1SutionSHAvg": "19.10",
"slave2SutionSHAvg": "0.00",
"slave3SutionSHAvg": "0.00",
"masterSuperCoolAvg": "1.80",
"slave1SuperCoolAvg": "1.80",
"slave2SuperCoolAvg": "0.00",
"slave3SuperCoolAvg": "0.00",
"masterINV1DichargeTempAvg": "74",
"slave1INV1DichargeTempAvg": "75",
"slave2INV1DichargeTempAvg": "300",
"slave3INV1DichargeTempAvg": "300",
"masterINV2DichargeTempAvg": "300",
"slave1INV2DichargeTempAvg": "300",
"slave2INV2DichargeTempAvg": "300",
"slave3INV2DichargeTempAvg": "300",
"masterINV1InputVoltageMin": "380",
"masterINV1InputVoltageMax": "380",
"masterINV1InputVoltageAvg": "380",
"slave1INV1InputVoltageMin": "375",
"slave1INV1InputVoltageMax": "375",
"slave1INV1InputVoltageAvg": "375",
"slave2INV1InputVoltageMin": "0",
"slave2INV1InputVoltageMax": "0",
"slave2INV1InputVoltageAvg": "0",
"slave3INV1InputVoltageMin": "0",
"slave3INV1InputVoltageMax": "0",
"slave3INV1InputVoltageAvg": "0",
"masterINV1InputCurrentMin": "6.60",
"masterINV1InputCurrentMax": "7.00",
"masterINV1InputCurrentAvg": "6.60",
"slave1INV1InputCurrentMin": "6.60",
"slave1INV1InputCurrentMax": "7.00",
"slave1INV1InputCurrentAvg": "6.60",
"slave2INV1InputCurrentMin": "0.00",
"slave2INV1InputCurrentMax": "0.00",
"slave2INV1InputCurrentAvg": "0.00",
"slave3INV1InputCurrentMin": "0.00",
"slave3INV1InputCurrentMax": "0.00",
"slave3INV1InputCurrentAvg": "0.00",
"masterINV1PhaseCurrentAvg": "13.80",
"slave1INV1PhaseCurrentAvg": "13.40",
"slave2INV1PhaseCurrentAvg": "0.00",
"slave3INV1PhaseCurrentAvg": "0.00",
"masterINV2PhaseCurrentAvg": "0.00",
"slave1INV2PhaseCurrentAvg": "0.00",
"slave2INV2PhaseCurrentAvg": "0.00",
"slave3INV2PhaseCurrentAvg": "0.00",
"capacityM": "12",
"capacityS1": "12",
"capacityS2": "0",
"capacityS3": "0",
"odu1EEPVersion": "79.94.11 / 79.94.11",
"odu2EEPVersion": "TEXT_ODU2_EEPVERSION_INFO",
"odu3EEPVersion": "TEXT_ODU3_EEPVERSION_INFO",
"odu4EEPVersion": "TEXT_ODU4_EEPVERSION_INFO",
"capacityRatio": "94",
"iduCapaSum": "228",
"systemError": "0",
"errorUnit": "63",
"SerialNumberM": "105KCHE0CL49",
"SerialNumberS1": "105KCPY0CL48",
"SerialNumberS2": "",
"SerialNumberS3": "",
"ModelNameM": "RPUW12GX9E",
"ModelNameS1": "RPUW12GX9E",
"ModelNameS2": "",
"ModelNameS3": "",
"LGMVVersionString": "1.0.8"}